sharphttp-0.3.0.dist-info/METADATA
sharphttp-0.3.0.dist-info/WHEEL
sharphttp/__init__.py
sharphttp/sharphttp.cp312-win_amd64.pyd
sharphttp-0.3.0.dist-info/RECORD
