Metadata-Version: 2.3
Name: sharphttp
Version: 0.3.0
Classifier: Programming Language :: Rust
Classifier: Programming Language :: Python :: Implementation :: CPython
Classifier: Programming Language :: Python :: 3.7
Classifier: Programming Language :: Python :: 3.8
Classifier: Programming Language :: Python :: 3.9
Classifier: Programming Language :: Python :: 3.10
Classifier: Programming Language :: Python :: 3.11
Classifier: Programming Language :: Python :: 3.12
Classifier: Topic :: Internet :: WWW/HTTP
Classifier: Topic :: Software Development :: Libraries :: Python Modules
Classifier: License :: OSI Approved :: MIT License
Classifier: Operating System :: OS Independent
Summary: A fast HTTP client implementation in Rust for Python
Keywords: http,client,async,rust
Author: acatto <nothanks@example.com>
Author-email: acatto <nothanks@example.com>
License: MIT
Requires-Python: >=3.7
Project-URL: Homepage, https://github.com/theoneandonlyacatto/sharphttp
